{"\rpuppet\nPUPPET_PUPPETEER":[{"name":"wxpluginkey","value":"1566133337","domain":".wx2.qq.com","path":"/","expires":1566182574,"size":21,"httpOnly":false,"secure":true,"session":false},{"name":"wxuin","value":"2916699812","domain":".wx2.qq.com","path":"/","expires":1566398574,"size":15,"httpOnly":false,"secure":true,"session":false},{"name":"MM_WX_SOUND_STATE","value":"1","domain":"wx2.qq.com","path":"/","expires":-1,"size":18,"httpOnly":false,"secure":false,"session":true},{"name":"MM_WX_NOTIFY_STATE","value":"1","domain":"wx2.qq.com","path":"/","expires":-1,"size":19,"httpOnly":false,"secure":false,"session":true},{"name":"mm_lang","value":"en_US","domain":".wx2.qq.com","path":"/","expires":1566164845,"size":12,"httpOnly":false,"secure":true,"session":false},{"name":"webwx_auth_ticket","value":"CIsBELajpqUBGoABV57sGJ4HiK3tDtuggQkBI/qy5FJntURYtJBvy0plWjM4977H0bv9TthUWSmB7U75qcp+AsYAfObtJri5sGCmauO3VrCckv+jXXwmfV4kK6Cxz9wJ14/seWYZhv4Iwyb7o8eRLZXM66qlZwkGk7/fs3wrQOhIPkOwXvEsuRwVKc8=","domain":".wx2.qq.com","path":"/","expires":1881472090,"size":205,"httpOnly":false,"secure":true,"session":false},{"name":"wxsid","value":"+qrS0bIepv5mtlD/","domain":".wx2.qq.com","path":"/","expires":1566182574,"size":21,"httpOnly":false,"secure":true,"session":false},{"name":"webwx_data_ticket","value":"gSe9ACmOGbR/y/epGuzZuvjP","domain":".qq.com","path":"/","expires":1566182574,"size":41,"httpOnly":false,"secure":true,"session":false},{"name":"last_wxuin","value":"2916699812","domain":"wx2.qq.com","path":"/","expires":1566284888,"size":20,"httpOnly":false,"secure":true,"session":false},{"name":"webwxuvid","value":"5740f4fda187902b31749c0da33f95397ed2fbcab2844759d92feaf118b50855acb4d625dc792ca4c2e17e7fc48dbaff","domain":".wx2.qq.com","path":"/","expires":1881286303,"size":105,"httpOnly":false,"secure":true,"session":false},{"name":"wxloadtime","value":"1566112090_expired","domain":".wx2.qq.com","path":"/","expires":1566155292,"size":28,"httpOnly":false,"secure":true,"session":false},{"name":"login_frequency","value":"1","domain":"wx2.qq.com","path":"/","expires":1566284888,"size":16,"httpOnly":false,"secure":true,"session":false}]}